Metadata-Version: 1.1
Name: tc-player
Version: 1.0.1
Summary: A Time Clickers automaton.
Home-page: https://github.com/colons/tc
Author: colons
Author-email: pypi@colons.co
License: LICENSE
Platform: any
Classifier: Operating System :: OS Independent
